{
    "clouds":[
       {
          "var1" : "130",
          "var2" : "140"
       },
       {
          "var1" : "25",
          "var2" : "80"
       },
       {
          "var1" : "130",
          "var2" : "60"
       },
       {  
          "var1" : "214",
          "var2" : "25"
       },
       {
          "var1" : "266",
          "var2" : "45"
       },
       {
          "var1" : "60",
          "var2" : "28"
       },
       {  
          "var1" : "370",
          "var2" : "30"
       },
       {
          "var1" : "160",
          "var2" : "125"
       },
       {  
          "var1" : "290",
          "var2" : "140"
       },
       {  
          "var1" : "260",
          "var2" : "110"
       }
    ]
 }